fr_date/__init__.py
fr_date/test_frdate.py
fr_date-2.0.7.dist-info/LICENSE
fr_date-2.0.7.dist-info/METADATA
fr_date-2.0.7.dist-info/WHEEL
fr_date-2.0.7.dist-info/top_level.txt
fr_date-2.0.7.dist-info/RECORD
