Metadata-Version: 2.1
Name: fr-date
Version: 2.0.7
Summary: Converts french text to python date object
Author-email: Thibaut_S <py@spriet.online>
License: MIT-License
Project-URL: Homepage, https://gitlab.com/outils-jcp/fr-date
Project-URL: Bug Tracker, https://gitlab.com/outils-jcp/fr-date/-/issues
Keywords: dates,french,français,conversion
Classifier: Programming Language :: Python :: 3
Requires-Python: >=3.8
License-File: LICENSE
Requires-Dist: dateutils
Requires-Dist: euros
Provides-Extra: dev
Requires-Dist: wheel ; extra == 'dev'
Requires-Dist: pytest ; extra == 'dev'
Requires-Dist: ruff ; extra == 'dev'
Requires-Dist: black ; extra == 'dev'
Requires-Dist: pip-tools ; extra == 'dev'
Requires-Dist: twine ; extra == 'dev'
